{
  "code": "sewingkit",
  "class": "Item",
  "tags": [
    "apprentice-content"
  ],
  "maxstacksize": 1,
  "storageFlags": 5,
  "shape": {
    "base": "apprentice:item/2.7/kit-sewing"
  },
  "textures": {
    "base": {
      "base": "apprentice:item/2.7/sewingkit"
    }
  },
  "creativeinventory": {
    "general": [
      "*"
    ],
    "items": [
      "*"
    ]
  },
  "guiTransform": {
    "rotation": {
      "x": -20,
      "y": 12,
      "z": 5
    },
    "scale": 1.6
  },
  "fpHandTransform": {
    "translation": { "x": -0.15, "y": -0.2, "z": 0.25 },
    "rotation": { "x": 10, "y": 100, "z": 15 },
    "scale": 1.1
  },
  "groundTransform": {
    "rotation": { "x": 0, "y": 30, "z": 90 },
    "scale": 1
  },
  "tpHandTransform": {
    "translation": { "x": -0.45, "y": 0, "z": -0.35 },
    "rotation": { "x": 80, "y": 0, "z": 10 },
    "scale": 0.65
  },
  "durability": 700,
  "attributes": {
    "apprenticeFeature": "sewing",
    "noConsumeOnCrafting": true
  }
}
